{"name":"Delete song","id":"deletesong;delete-song","testSteps":[{"number":1,"description":"Delete song #1: {id\u003d7}","duration":6121,"startTime":"2018-09-04T10:11:50.522-05:00[America/Bogota]","result":"SUCCESS","precondition":false,"children":[{"number":2,"description":"Given I have access to  Kafka Service","duration":16,"startTime":"2018-09-04T10:11:50.524-05:00[America/Bogota]","result":"SUCCESS","precondition":false},{"number":3,"description":"And the song with this \"7\" exists","duration":5010,"startTime":"2018-09-04T10:11:50.540-05:00[America/Bogota]","result":"SUCCESS","precondition":false,"children":[{"number":4,"description":"GET http://localhost:7070/kafka-music/song/7\r\r","duration":2,"startTime":"2018-09-04T10:11:55.475-05:00[America/Bogota]","result":"SUCCESS","restQuery":{"method":"GET","path":"http://localhost:7070/kafka-music/song/7\r\r","content":"\r","contentType":"application/json","requestHeaders":"Accept\u003d*/*\r\n\t\t\t\tContent-Type\u003dapplication/json; charset\u003dUTF-8\r\r","requestCookies":"\r\r","responseHeaders":"Date: Tue, 04 Sep 2018 15:11:55 GMT\nContent-Type: application/json\nContent-Length: 85\nServer: Jetty(9.2.z-SNAPSHOT)\r","responseCookies":"\r","responseBody":"{\n    \"artist\": \"The Beastie Boys\",\n    \"album\": \"Licensed to Ill\",\n    \"name\": \"Fight For Your Right\"\n}","statusCode":200},"precondition":false}]},{"number":5,"description":"When I delete a song with that \"7\"","duration":48,"startTime":"2018-09-04T10:11:55.551-05:00[America/Bogota]","result":"SUCCESS","precondition":false},{"number":6,"description":"Then I wont see the song with that \"7\"","duration":1043,"startTime":"2018-09-04T10:11:55.600-05:00[America/Bogota]","result":"SUCCESS","precondition":false,"children":[{"number":7,"description":"GET http://localhost:7070/kafka-music/song/7\r\r","duration":0,"startTime":"2018-09-04T10:11:56.640-05:00[America/Bogota]","result":"SUCCESS","restQuery":{"method":"GET","path":"http://localhost:7070/kafka-music/song/7\r\r","content":"\r","contentType":"application/json","requestHeaders":"Accept\u003d*/*\r\n\t\t\t\tContent-Type\u003dapplication/json; charset\u003dUTF-8\r\r","requestCookies":"\r\r","responseHeaders":"Date: Tue, 04 Sep 2018 15:11:56 GMT\nContent-Type: application/json\nContent-Length: 34\nServer: Jetty(9.2.z-SNAPSHOT)\r","responseCookies":"\r","responseBody":"{\n    \"artist\": \"\",\n    \"album\": \"\",\n    \"name\": \"\"\n}","statusCode":200},"precondition":false}]}]}],"userStory":{"id":"deletesong","storyName":"Deletesong","path":"src/test/resources/features/deleteSong.feature","narrative":"  As kafka administrator\n  I want to delete an existing song\n  so that the song won\u0027t be visible","type":"feature"},"featureTag":{"name":"Features/Deletesong","type":"feature"},"title":"Delete song","startTime":"2018-09-04T10:11:50.519-05:00[America/Bogota]","duration":6639,"projectKey":"","dataTable":{"headers":["id"],"rows":[{"values":["7"],"result":"SUCCESS"}],"predefinedRows":true,"scenarioOutline":"Given I have access to  Kafka Service\n\rAnd the song with this \"\u003cid\u003e\" exists\n\rWhen I delete a song with that \"\u003cid\u003e\"\n\rThen I wont see the song with that \"\u003cid\u003e\"\n\r","dataSetDescriptors":[{"startRow":0,"rowCount":0,"name":""}]},"manual":false,"testSource":"Cucumber","result":"SUCCESS"}